BIST/adress_gen.v
module adr_gen #(parameter ADR_SIZE = 4) (clk, rst_adr, pr_res_adr, enable, up_down, adress, c_out);

input clk, rst_adr, pr_res_adr, enable, up_down;
output reg [ADR_SIZE-1:0] adress;
output reg c_out;

wire a, b;

assign a = (adress=={{ADR_SIZE-1{1'b1}},1'b0} && up_down && enable) ? 1'b1 : 1'b0;
assign b = (adress=={{ADR_SIZE-1{1'b0}},1'b1} && !up_down && enable) ? 1'b1 : 1'b0;

always@(posedge clk)begin
	if(up_down) c_out<=a;
    else c_out<=b;	
end

always@(posedge clk)begin
	if(rst_adr) adress <= {ADR_SIZE{1'b0}};
	else if (pr_res_adr) adress <={ADR_SIZE{1'b1}};
	else if (enable) begin
		if(up_down) adress <= adress+{{ADR_SIZE-1{1'b0}},1'b1};
		else adress <= adress-{{ADR_SIZE-1{1'b0}},1'b1};
	end
end
endmodule

BIST/all/adress_gen/tb_counter.v
module tbcnt();
parameter Adr_size=8;

reg clk, rst, pr_rst, enable, up_down;

wire [Adr_size-1:0] adress;
wire c_out;

adr_gen gen (.clk(clk), .rst_adr(rst), .pr_res_adr(pr_rst), .enable(enable), .up_down(up_down), .adress(adress), .c_out(c_out)); 

always #1 clk = ~clk;
initial begin
	clk=1'b0;
	$dumpfile("mem.vcd");
    $dumpvars();
    end

initial begin
	rst=1'b1;
	pr_rst=1'b0;
	enable=1'b0;
	up_down=1'b1;
	#20;
	rst=1'b0;
	pr_rst=1'b0;
	enable=1'b0;
	up_down=1'b1;
	#20;
	rst=1'b0;
	pr_rst=1'b0;
	enable=1'b1;
	up_down=1'b1;
	#990;
	rst=1'b0;
	pr_rst=1'b1;
	#5;
	pr_rst=1'b0;
	enable=1'b1;
	up_down=1'b0;
	#990;
	rst=1'b0;
	pr_rst=1'b0;
	enable=1'b0;
	up_down=1'b0;
	#200;
	$finish;

	end
endmodule

BIST/all/adress_gen/mem.vcd
$date
	Sun Jun 25 12:21:13 2023
$end
$version
	Icarus Verilog
$end
$timescale
	1s
$end
$scope module tbcnt $end
$var wire 1 ! c_out $end
$var wire 8 " adress [7:0] $end
$var reg 1 # clk $end
$var reg 1 $ enable $end
$var reg 1 % pr_rst $end
$var reg 1 & rst $end
$var reg 1 ' up_down $end
$scope module gen $end
$var wire 1 # clk $end
$var wire 1 $ enable $end
$var wire 1 % pr_res_adr $end
$var wire 1 & rst_adr $end
$var wire 1 ' up_down $end
$var wire 1 ( b $end
$var wire 1 ) a $end
$var reg 8 * adress [7:0] $end
$var reg 1 ! c_out $end
$upscope $end
$upscope $end
$enddefinitions $end
#0
$dumpvars
bx *
x)
0(
1'
1&
0%
0$
0#
bx "
x!
$end
#1
0!
0)
b0 "
b0 *
1#
#2
0#
#3
1#
#4
0#
#5
1#
#6
0#
#7
1#
#8
0#
#9
1#
#10
0#
#11
1#
#12
0#
#13
1#
#14
0#
#15
1#
#16
0#
#17
1#
#18
0#
#19
1#
#20
0#
0&
#21
1#
#22
0#
#23
1#
#24
0#
#25
1#
#26
0#
#27
1#
#28
0#
#29
1#
#30
0#
#31
1#
#32
0#
#33
1#
#34
0#
#35
1#
#36
0#
#37
1#
#38
0#
#39
1#
#40
0#
1$
#41
b1 "
b1 *
1#
#42
0#
#43
b10 "
b10 *
1#
#44
0#
#45
b11 "
b11 *
1#
#46
0#
#47
b100 "
b100 *
1#
#48
0#
#49
b101 "
b101 *
1#
#50
0#
#51
b110 "
b110 *
1#
#52
0#
#53
b111 "
b111 *
1#
#54
0#
#55
b1000 "
b1000 *
1#
#56
0#
#57
b1001 "
b1001 *
1#
#58
0#
#59
b1010 "
b1010 *
1#
#60
0#
#61
b1011 "
b1011 *
1#
#62
0#
#63
b1100 "
b1100 *
1#
#64
0#
#65
b1101 "
b1101 *
1#
#66
0#
#67
b1110 "
b1110 *
1#
#68
0#
#69
b1111 "
b1111 *
1#
#70
0#
#71
b10000 "
b10000 *
1#
#72
0#
#73
b10001 "
b10001 *
1#
#74
0#
#75
b10010 "
b10010 *
1#
#76
0#
#77
b10011 "
b10011 *
1#
#78
0#
#79
b10100 "
b10100 *
1#
#80
0#
#81
b10101 "
b10101 *
1#
#82
0#
#83
b10110 "
b10110 *
1#
#84
0#
#85
b10111 "
b10111 *
1#
#86
0#
#87
b11000 "
b11000 *
1#
#88
0#
#89
b11001 "
b11001 *
1#
#90
0#
#91
b11010 "
b11010 *
1#
#92
0#
#93
b11011 "
b11011 *
1#
#94
0#
#95
b11100 "
b11100 *
1#
#96
0#
#97
b11101 "
b11101 *
1#
#98
0#
#99
b11110 "
b11110 *
1#
#100
0#
#101
b11111 "
b11111 *
1#
#102
0#
#103
b100000 "
b100000 *
1#
#104
0#
#105
b100001 "
b100001 *
1#
#106
0#
#107
b100010 "
b100010 *
1#
#108
0#
#109
b100011 "
b100011 *
1#
#110
0#
#111
b100100 "
b100100 *
1#
#112
0#
#113
b100101 "
b100101 *
1#
#114
0#
#115
b100110 "
b100110 *
1#
#116
0#
#117
b100111 "
b100111 *
1#
#118
0#
#119
b101000 "
b101000 *
1#
#120
0#
#121
b101001 "
b101001 *
1#
#122
0#
#123
b101010 "
b101010 *
1#
#124
0#
#125
b101011 "
b101011 *
1#
#126
0#
#127
b101100 "
b101100 *
1#
#128
0#
#129
b101101 "
b101101 *
1#
#130
0#
#131
b101110 "
b101110 *
1#
#132
0#
#133
b101111 "
b101111 *
1#
#134
0#
#135
b110000 "
b110000 *
1#
#136
0#
#137
b110001 "
b110001 *
1#
#138
0#
#139
b110010 "
b110010 *
1#
#140
0#
#141
b110011 "
b110011 *
1#
#142
0#
#143
b110100 "
b110100 *
1#
#144
0#
#145
b110101 "
b110101 *
1#
#146
0#
#147
b110110 "
b110110 *
1#
#148
0#
#149
b110111 "
b110111 *
1#
#150
0#
#151
b111000 "
b111000 *
1#
#152
0#
#153
b111001 "
b111001 *
1#
#154
0#
#155
b111010 "
b111010 *
1#
#156
0#
#157
b111011 "
b111011 *
1#
#158
0#
#159
b111100 "
b111100 *
1#
#160
0#
#161
b111101 "
b111101 *
1#
#162
0#
#163
b111110 "
b111110 *
1#
#164
0#
#165
b111111 "
b111111 *
1#
#166
0#
#167
b1000000 "
b1000000 *
1#
#168
0#
#169
b1000001 "
b1000001 *
1#
#170
0#
#171
b1000010 "
b1000010 *
1#
#172
0#
#173
b1000011 "
b1000011 *
1#
#174
0#
#175
b1000100 "
b1000100 *
1#
#176
0#
#177
b1000101 "
b1000101 *
1#
#178
0#
#179
b1000110 "
b1000110 *
1#
#180
0#
#181
b1000111 "
b1000111 *
1#
#182
0#
#183
b1001000 "
b1001000 *
1#
#184
0#
#185
b1001001 "
b1001001 *
1#
#186
0#
#187
b1001010 "
b1001010 *
1#
#188
0#
#189
b1001011 "
b1001011 *
1#
#190
0#
#191
b1001100 "
b1001100 *
1#
#192
0#
#193
b1001101 "
b1001101 *
1#
#194
0#
#195
b1001110 "
b1001110 *
1#
#196
0#
#197
b1001111 "
b1001111 *
1#
#198
0#
#199
b1010000 "
b1010000 *
1#
#200
0#
#201
b1010001 "
b1010001 *
1#
#202
0#
#203
b1010010 "
b1010010 *
1#
#204
0#
#205
b1010011 "
b1010011 *
1#
#206
0#
#207
b1010100 "
b1010100 *
1#
#208
0#
#209
b1010101 "
b1010101 *
1#
#210
0#
#211
b1010110 "
b1010110 *
1#
#212
0#
#213
b1010111 "
b1010111 *
1#
#214
0#
#215
b1011000 "
b1011000 *
1#
#216
0#
#217
b1011001 "
b1011001 *
1#
#218
0#
#219
b1011010 "
b1011010 *
1#
#220
0#
#221
b1011011 "
b1011011 *
1#
#222
0#
#223
b1011100 "
b1011100 *
1#
#224
0#
#225
b1011101 "
b1011101 *
1#
#226
0#
#227
b1011110 "
b1011110 *
1#
#228
0#
#229
b1011111 "
b1011111 *
1#
#230
0#
#231
b1100000 "
b1100000 *
1#
#232
0#
#233
b1100001 "
b1100001 *
1#
#234
0#
#235
b1100010 "
b1100010 *
1#
#236
0#
#237
b1100011 "
b1100011 *
1#
#238
0#
#239
b1100100 "
b1100100 *
1#
#240
0#
#241
b1100101 "
b1100101 *
1#
#242
0#
#243
b1100110 "
b1100110 *
1#
#244
0#
#245
b1100111 "
b1100111 *
1#
#246
0#
#247
b1101000 "
b1101000 *
1#
#248
0#
#249
b1101001 "
b1101001 *
1#
#250
0#
#251
b1101010 "
b1101010 *
1#
#252
0#
#253
b1101011 "
b1101011 *
1#
#254
0#
#255
b1101100 "
b1101100 *
1#
#256
0#
#257
b1101101 "
b1101101 *
1#
#258
0#
#259
b1101110 "
b1101110 *
1#
#260
0#
#261
b1101111 "
b1101111 *
1#
#262
0#
#263
b1110000 "
b1110000 *
1#
#264
0#
#265
b1110001 "
b1110001 *
1#
#266
0#
#267
b1110010 "
b1110010 *
1#
#268
0#
#269
b1110011 "
b1110011 *
1#
#270
0#
#271
b1110100 "
b1110100 *
1#
#272
0#
#273
b1110101 "
b1110101 *
1#
#274
0#
#275
b1110110 "
b1110110 *
1#
#276
0#
#277
b1110111 "
b1110111 *
1#
#278
0#
#279
b1111000 "
b1111000 *
1#
#280
0#
#281
b1111001 "
b1111001 *
1#
#282
0#
#283
b1111010 "
b1111010 *
1#
#284
0#
#285
b1111011 "
b1111011 *
1#
#286
0#
#287
b1111100 "
b1111100 *
1#
#288
0#
#289
b1111101 "
b1111101 *
1#
#290
0#
#291
b1111110 "
b1111110 *
1#
#292
0#
#293
b1111111 "
b1111111 *
1#
#294
0#
#295
b10000000 "
b10000000 *
1#
#296
0#
#297
b10000001 "
b10000001 *
1#
#298
0#
#299
b10000010 "
b10000010 *
1#
#300
0#
#301
b10000011 "
b10000011 *
1#
#302
0#
#303
b10000100 "
b10000100 *
1#
#304
0#
#305
b10000101 "
b10000101 *
1#
#306
0#
#307
b10000110 "
b10000110 *
1#
#308
0#
#309
b10000111 "
b10000111 *
1#
#310
0#
#311
b10001000 "
b10001000 *
1#
#312
0#
#313
b10001001 "
b10001001 *
1#
#314
0#
#315
b10001010 "
b10001010 *
1#
#316
0#
#317
b10001011 "
b10001011 *
1#
#318
0#
#319
b10001100 "
b10001100 *
1#
#320
0#
#321
b10001101 "
b10001101 *
1#
#322
0#
#323
b10001110 "
b10001110 *
1#
#324
0#
#325
b10001111 "
b10001111 *
1#
#326
0#
#327
b10010000 "
b10010000 *
1#
#328
0#
#329
b10010001 "
b10010001 *
1#
#330
0#
#331
b10010010 "
b10010010 *
1#
#332
0#
#333
b10010011 "
b10010011 *
1#
#334
0#
#335
b10010100 "
b10010100 *
1#
#336
0#
#337
b10010101 "
b10010101 *
1#
#338
0#
#339
b10010110 "
b10010110 *
1#
#340
0#
#341
b10010111 "
b10010111 *
1#
#342
0#
#343
b10011000 "
b10011000 *
1#
#344
0#
#345
b10011001 "
b10011001 *
1#
#346
0#
#347
b10011010 "
b10011010 *
1#
#348
0#
#349
b10011011 "
b10011011 *
1#
#350
0#
#351
b10011100 "
b10011100 *
1#
#352
0#
#353
b10011101 "
b10011101 *
1#
#354
0#
#355
b10011110 "
b10011110 *
1#
#356
0#
#357
b10011111 "
b10011111 *
1#
#358
0#
#359
b10100000 "
b10100000 *
1#
#360
0#
#361
b10100001 "
b10100001 *
1#
#362
0#
#363
b10100010 "
b10100010 *
1#
#364
0#
#365
b10100011 "
b10100011 *
1#
#366
0#
#367
b10100100 "
b10100100 *
1#
#368
0#
#369
b10100101 "
b10100101 *
1#
#370
0#
#371
b10100110 "
b10100110 *
1#
#372
0#
#373
b10100111 "
b10100111 *
1#
#374
0#
#375
b10101000 "
b10101000 *
1#
#376
0#
#377
b10101001 "
b10101001 *
1#
#378
0#
#379
b10101010 "
b10101010 *
1#
#380
0#
#381
b10101011 "
b10101011 *
1#
#382
0#
#383
b10101100 "
b10101100 *
1#
#384
0#
#385
b10101101 "
b10101101 *
1#
#386
0#
#387
b10101110 "
b10101110 *
1#
#388
0#
#389
b10101111 "
b10101111 *
1#
#390
0#
#391
b10110000 "
b10110000 *
1#
#392
0#
#393
b10110001 "
b10110001 *
1#
#394
0#
#395
b10110010 "
b10110010 *
1#
#396
0#
#397
b10110011 "
b10110011 *
1#
#398
0#
#399
b10110100 "
b10110100 *
1#
#400
0#
#401
b10110101 "
b10110101 *
1#
#402
0#
#403
b10110110 "
b10110110 *
1#
#404
0#
#405
b10110111 "
b10110111 *
1#
#406
0#
#407
b10111000 "
b10111000 *
1#
#408
0#
#409
b10111001 "
b10111001 *
1#
#410
0#
#411
b10111010 "
b10111010 *
1#
#412
0#
#413
b10111011 "
b10111011 *
1#
#414
0#
#415
b10111100 "
b10111100 *
1#
#416
0#
#417
b10111101 "
b10111101 *
1#
#418
0#
#419
b10111110 "
b10111110 *
1#
#420
0#
#421
b10111111 "
b10111111 *
1#
#422
0#
#423
b11000000 "
b11000000 *
1#
#424
0#
#425
b11000001 "
b11000001 *
1#
#426
0#
#427
b11000010 "
b11000010 *
1#
#428
0#
#429
b11000011 "
b11000011 *
1#
#430
0#
#431
b11000100 "
b11000100 *
1#
#432
0#
#433
b11000101 "
b11000101 *
1#
#434
0#
#435
b11000110 "
b11000110 *
1#
#436
0#
#437
b11000111 "
b11000111 *
1#
#438
0#
#439
b11001000 "
b11001000 *
1#
#440
0#
#441
b11001001 "
b11001001 *
1#
#442
0#
#443
b11001010 "
b11001010 *
1#
#444
0#
#445
b11001011 "
b11001011 *
1#
#446
0#
#447
b11001100 "
b11001100 *
1#
#448
0#
#449
b11001101 "
b11001101 *
1#
#450
0#
#451
b11001110 "
b11001110 *
1#
#452
0#
#453
b11001111 "
b11001111 *
1#
#454
0#
#455
b11010000 "
b11010000 *
1#
#456
0#
#457
b11010001 "
b11010001 *
1#
#458
0#
#459
b11010010 "
b11010010 *
1#
#460
0#
#461
b11010011 "
b11010011 *
1#
#462
0#
#463
b11010100 "
b11010100 *
1#
#464
0#
#465
b11010101 "
b11010101 *
1#
#466
0#
#467
b11010110 "
b11010110 *
1#
#468
0#
#469
b11010111 "
b11010111 *
1#
#470
0#
#471
b11011000 "
b11011000 *
1#
#472
0#
#473
b11011001 "
b11011001 *
1#
#474
0#
#475
b11011010 "
b11011010 *
1#
#476
0#
#477
b11011011 "
b11011011 *
1#
#478
0#
#479
b11011100 "
b11011100 *
1#
#480
0#
#481
b11011101 "
b11011101 *
1#
#482
0#
#483
b11011110 "
b11011110 *
1#
#484
0#
#485
b11011111 "
b11011111 *
1#
#486
0#
#487
b11100000 "
b11100000 *
1#
#488
0#
#489
b11100001 "
b11100001 *
1#
#490
0#
#491
b11100010 "
b11100010 *
1#
#492
0#
#493
b11100011 "
b11100011 *
1#
#494
0#
#495
b11100100 "
b11100100 *
1#
#496
0#
#497
b11100101 "
b11100101 *
1#
#498
0#
#499
b11100110 "
b11100110 *
1#
#500
0#
#501
b11100111 "
b11100111 *
1#
#502
0#
#503
b11101000 "
b11101000 *
1#
#504
0#
#505
b11101001 "
b11101001 *
1#
#506
0#
#507
b11101010 "
b11101010 *
1#
#508
0#
#509
b11101011 "
b11101011 *
1#
#510
0#
#511
b11101100 "
b11101100 *
1#
#512
0#
#513
b11101101 "
b11101101 *
1#
#514
0#
#515
b11101110 "
b11101110 *
1#
#516
0#
#517
b11101111 "
b11101111 *
1#
#518
0#
#519
b11110000 "
b11110000 *
1#
#520
0#
#521
b11110001 "
b11110001 *
1#
#522
0#
#523
b11110010 "
b11110010 *
1#
#524
0#
#525
b11110011 "
b11110011 *
1#
#526
0#
#527
b11110100 "
b11110100 *
1#
#528
0#
#529
b11110101 "
b11110101 *
1#
#530
0#
#531
b11110110 "
b11110110 *
1#
#532
0#
#533
b11110111 "
b11110111 *
1#
#534
0#
#535
b11111000 "
b11111000 *
1#
#536
0#
#537
b11111001 "
b11111001 *
1#
#538
0#
#539
b11111010 "
b11111010 *
1#
#540
0#
#541
b11111011 "
b11111011 *
1#
#542
0#
#543
b11111100 "
b11111100 *
1#
#544
0#
#545
b11111101 "
b11111101 *
1#
#546
0#
#547
1!
1)
b11111110 "
b11111110 *
1#
#548
0#
#549
0!
0)
b11111111 "
b11111111 *
1#
#550
0#
#551
b0 "
b0 *
1#
#552
0#
#553
b1 "
b1 *
1#
#554
0#
#555
b10 "
b10 *
1#
#556
0#
#557
b11 "
b11 *
1#
#558
0#
#559
b100 "
b100 *
1#
#560
0#
#561
b101 "
b101 *
1#
#562
0#
#563
b110 "
b110 *
1#
#564
0#
#565
b111 "
b111 *
1#
#566
0#
#567
b1000 "
b1000 *
1#
#568
0#
#569
b1001 "
b1001 *
1#
#570
0#
#571
b1010 "
b1010 *
1#
#572
0#
#573
b1011 "
b1011 *
1#
#574
0#
#575
b1100 "
b1100 *
1#
#576
0#
#577
b1101 "
b1101 *
1#
#578
0#
#579
b1110 "
b1110 *
1#
#580
0#
#581
b1111 "
b1111 *
1#
#582
0#
#583
b10000 "
b10000 *
1#
#584
0#
#585
b10001 "
b10001 *
1#
#586
0#
#587
b10010 "
b10010 *
1#
#588
0#
#589
b10011 "
b10011 *
1#
#590
0#
#591
b10100 "
b10100 *
1#
#592
0#
#593
b10101 "
b10101 *
1#
#594
0#
#595
b10110 "
b10110 *
1#
#596
0#
#597
b10111 "
b10111 *
1#
#598
0#
#599
b11000 "
b11000 *
1#
#600
0#
#601
b11001 "
b11001 *
1#
#602
0#
#603
b11010 "
b11010 *
1#
#604
0#
#605
b11011 "
b11011 *
1#
#606
0#
#607
b11100 "
b11100 *
1#
#608
0#
#609
b11101 "
b11101 *
1#
#610
0#
#611
b11110 "
b11110 *
1#
#612
0#
#613
b11111 "
b11111 *
1#
#614
0#
#615
b100000 "
b100000 *
1#
#616
0#
#617
b100001 "
b100001 *
1#
#618
0#
#619
b100010 "
b100010 *
1#
#620
0#
#621
b100011 "
b100011 *
1#
#622
0#
#623
b100100 "
b100100 *
1#
#624
0#
#625
b100101 "
b100101 *
1#
#626
0#
#627
b100110 "
b100110 *
1#
#628
0#
#629
b100111 "
b100111 *
1#
#630
0#
#631
b101000 "
b101000 *
1#
#632
0#
#633
b101001 "
b101001 *
1#
#634
0#
#635
b101010 "
b101010 *
1#
#636
0#
#637
b101011 "
b101011 *
1#
#638
0#
#639
b101100 "
b101100 *
1#
#640
0#
#641
b101101 "
b101101 *
1#
#642
0#
#643
b101110 "
b101110 *
1#
#644
0#
#645
b101111 "
b101111 *
1#
#646
0#
#647
b110000 "
b110000 *
1#
#648
0#
#649
b110001 "
b110001 *
1#
#650
0#
#651
b110010 "
b110010 *
1#
#652
0#
#653
b110011 "
b110011 *
1#
#654
0#
#655
b110100 "
b110100 *
1#
#656
0#
#657
b110101 "
b110101 *
1#
#658
0#
#659
b110110 "
b110110 *
1#
#660
0#
#661
b110111 "
b110111 *
1#
#662
0#
#663
b111000 "
b111000 *
1#
#664
0#
#665
b111001 "
b111001 *
1#
#666
0#
#667
b111010 "
b111010 *
1#
#668
0#
#669
b111011 "
b111011 *
1#
#670
0#
#671
b111100 "
b111100 *
1#
#672
0#
#673
b111101 "
b111101 *
1#
#674
0#
#675
b111110 "
b111110 *
1#
#676
0#
#677
b111111 "
b111111 *
1#
#678
0#
#679
b1000000 "
b1000000 *
1#
#680
0#
#681
b1000001 "
b1000001 *
1#
#682
0#
#683
b1000010 "
b1000010 *
1#
#684
0#
#685
b1000011 "
b1000011 *
1#
#686
0#
#687
b1000100 "
b1000100 *
1#
#688
0#
#689
b1000101 "
b1000101 *
1#
#690
0#
#691
b1000110 "
b1000110 *
1#
#692
0#
#693
b1000111 "
b1000111 *
1#
#694
0#
#695
b1001000 "
b1001000 *
1#
#696
0#
#697
b1001001 "
b1001001 *
1#
#698
0#
#699
b1001010 "
b1001010 *
1#
#700
0#
#701
b1001011 "
b1001011 *
1#
#702
0#
#703
b1001100 "
b1001100 *
1#
#704
0#
#705
b1001101 "
b1001101 *
1#
#706
0#
#707
b1001110 "
b1001110 *
1#
#708
0#
#709
b1001111 "
b1001111 *
1#
#710
0#
#711
b1010000 "
b1010000 *
1#
#712
0#
#713
b1010001 "
b1010001 *
1#
#714
0#
#715
b1010010 "
b1010010 *
1#
#716
0#
#717
b1010011 "
b1010011 *
1#
#718
0#
#719
b1010100 "
b1010100 *
1#
#720
0#
#721
b1010101 "
b1010101 *
1#
#722
0#
#723
b1010110 "
b1010110 *
1#
#724
0#
#725
b1010111 "
b1010111 *
1#
#726
0#
#727
b1011000 "
b1011000 *
1#
#728
0#
#729
b1011001 "
b1011001 *
1#
#730
0#
#731
b1011010 "
b1011010 *
1#
#732
0#
#733
b1011011 "
b1011011 *
1#
#734
0#
#735
b1011100 "
b1011100 *
1#
#736
0#
#737
b1011101 "
b1011101 *
1#
#738
0#
#739
b1011110 "
b1011110 *
1#
#740
0#
#741
b1011111 "
b1011111 *
1#
#742
0#
#743
b1100000 "
b1100000 *
1#
#744
0#
#745
b1100001 "
b1100001 *
1#
#746
0#
#747
b1100010 "
b1100010 *
1#
#748
0#
#749
b1100011 "
b1100011 *
1#
#750
0#
#751
b1100100 "
b1100100 *
1#
#752
0#
#753
b1100101 "
b1100101 *
1#
#754
0#
#755
b1100110 "
b1100110 *
1#
#756
0#
#757
b1100111 "
b1100111 *
1#
#758
0#
#759
b1101000 "
b1101000 *
1#
#760
0#
#761
b1101001 "
b1101001 *
1#
#762
0#
#763
b1101010 "
b1101010 *
1#
#764
0#
#765
b1101011 "
b1101011 *
1#
#766
0#
#767
b1101100 "
b1101100 *
1#
#768
0#
#769
b1101101 "
b1101101 *
1#
#770
0#
#771
b1101110 "
b1101110 *
1#
#772
0#
#773
b1101111 "
b1101111 *
1#
#774
0#
#775
b1110000 "
b1110000 *
1#
#776
0#
#777
b1110001 "
b1110001 *
1#
#778
0#
#779
b1110010 "
b1110010 *
1#
#780
0#
#781
b1110011 "
b1110011 *
1#
#782
0#
#783
b1110100 "
b1110100 *
1#
#784
0#
#785
b1110101 "
b1110101 *
1#
#786
0#
#787
b1110110 "
b1110110 *
1#
#788
0#
#789
b1110111 "
b1110111 *
1#
#790
0#
#791
b1111000 "
b1111000 *
1#
#792
0#
#793
b1111001 "
b1111001 *
1#
#794
0#
#795
b1111010 "
b1111010 *
1#
#796
0#
#797
b1111011 "
b1111011 *
1#
#798
0#
#799
b1111100 "
b1111100 *
1#
#800
0#
#801
b1111101 "
b1111101 *
1#
#802
0#
#803
b1111110 "
b1111110 *
1#
#804
0#
#805
b1111111 "
b1111111 *
1#
#806
0#
#807
b10000000 "
b10000000 *
1#
#808
0#
#809
b10000001 "
b10000001 *
1#
#810
0#
#811
b10000010 "
b10000010 *
1#
#812
0#
#813
b10000011 "
b10000011 *
1#
#814
0#
#815
b10000100 "
b10000100 *
1#
#816
0#
#817
b10000101 "
b10000101 *
1#
#818
0#
#819
b10000110 "
b10000110 *
1#
#820
0#
#821
b10000111 "
b10000111 *
1#
#822
0#
#823
b10001000 "
b10001000 *
1#
#824
0#
#825
b10001001 "
b10001001 *
1#
#826
0#
#827
b10001010 "
b10001010 *
1#
#828
0#
#829
b10001011 "
b10001011 *
1#
#830
0#
#831
b10001100 "
b10001100 *
1#
#832
0#
#833
b10001101 "
b10001101 *
1#
#834
0#
#835
b10001110 "
b10001110 *
1#
#836
0#
#837
b10001111 "
b10001111 *
1#
#838
0#
#839
b10010000 "
b10010000 *
1#
#840
0#
#841
b10010001 "
b10010001 *
1#
#842
0#
#843
b10010010 "
b10010010 *
1#
#844
0#
#845
b10010011 "
b10010011 *
1#
#846
0#
#847
b10010100 "
b10010100 *
1#
#848
0#
#849
b10010101 "
b10010101 *
1#
#850
0#
#851
b10010110 "
b10010110 *
1#
#852
0#
#853
b10010111 "
b10010111 *
1#
#854
0#
#855
b10011000 "
b10011000 *
1#
#856
0#
#857
b10011001 "
b10011001 *
1#
#858
0#
#859
b10011010 "
b10011010 *
1#
#860
0#
#861
b10011011 "
b10011011 *
1#
#862
0#
#863
b10011100 "
b10011100 *
1#
#864
0#
#865
b10011101 "
b10011101 *
1#
#866
0#
#867
b10011110 "
b10011110 *
1#
#868
0#
#869
b10011111 "
b10011111 *
1#
#870
0#
#871
b10100000 "
b10100000 *
1#
#872
0#
#873
b10100001 "
b10100001 *
1#
#874
0#
#875
b10100010 "
b10100010 *
1#
#876
0#
#877
b10100011 "
b10100011 *
1#
#878
0#
#879
b10100100 "
b10100100 *
1#
#880
0#
#881
b10100101 "
b10100101 *
1#
#882
0#
#883
b10100110 "
b10100110 *
1#
#884
0#
#885
b10100111 "
b10100111 *
1#
#886
0#
#887
b10101000 "
b10101000 *
1#
#888
0#
#889
b10101001 "
b10101001 *
1#
#890
0#
#891
b10101010 "
b10101010 *
1#
#892
0#
#893
b10101011 "
b10101011 *
1#
#894
0#
#895
b10101100 "
b10101100 *
1#
#896
0#
#897
b10101101 "
b10101101 *
1#
#898
0#
#899
b10101110 "
b10101110 *
1#
#900
0#
#901
b10101111 "
b10101111 *
1#
#902
0#
#903
b10110000 "
b10110000 *
1#
#904
0#
#905
b10110001 "
b10110001 *
1#
#906
0#
#907
b10110010 "
b10110010 *
1#
#908
0#
#909
b10110011 "
b10110011 *
1#
#910
0#
#911
b10110100 "
b10110100 *
1#
#912
0#
#913
b10110101 "
b10110101 *
1#
#914
0#
#915
b10110110 "
b10110110 *
1#
#916
0#
#917
b10110111 "
b10110111 *
1#
#918
0#
#919
b10111000 "
b10111000 *
1#
#920
0#
#921
b10111001 "
b10111001 *
1#
#922
0#
#923
b10111010 "
b10111010 *
1#
#924
0#
#925
b10111011 "
b10111011 *
1#
#926
0#
#927
b10111100 "
b10111100 *
1#
#928
0#
#929
b10111101 "
b10111101 *
1#
#930
0#
#931
b10111110 "
b10111110 *
1#
#932
0#
#933
b10111111 "
b10111111 *
1#
#934
0#
#935
b11000000 "
b11000000 *
1#
#936
0#
#937
b11000001 "
b11000001 *
1#
#938
0#
#939
b11000010 "
b11000010 *
1#
#940
0#
#941
b11000011 "
b11000011 *
1#
#942
0#
#943
b11000100 "
b11000100 *
1#
#944
0#
#945
b11000101 "
b11000101 *
1#
#946
0#
#947
b11000110 "
b11000110 *
1#
#948
0#
#949
b11000111 "
b11000111 *
1#
#950
0#
#951
b11001000 "
b11001000 *
1#
#952
0#
#953
b11001001 "
b11001001 *
1#
#954
0#
#955
b11001010 "
b11001010 *
1#
#956
0#
#957
b11001011 "
b11001011 *
1#
#958
0#
#959
b11001100 "
b11001100 *
1#
#960
0#
#961
b11001101 "
b11001101 *
1#
#962
0#
#963
b11001110 "
b11001110 *
1#
#964
0#
#965
b11001111 "
b11001111 *
1#
#966
0#
#967
b11010000 "
b11010000 *
1#
#968
0#
#969
b11010001 "
b11010001 *
1#
#970
0#
#971
b11010010 "
b11010010 *
1#
#972
0#
#973
b11010011 "
b11010011 *
1#
#974
0#
#975
b11010100 "
b11010100 *
1#
#976
0#
#977
b11010101 "
b11010101 *
1#
#978
0#
#979
b11010110 "
b11010110 *
1#
#980
0#
#981
b11010111 "
b11010111 *
1#
#982
0#
#983
b11011000 "
b11011000 *
1#
#984
0#
#985
b11011001 "
b11011001 *
1#
#986
0#
#987
b11011010 "
b11011010 *
1#
#988
0#
#989
b11011011 "
b11011011 *
1#
#990
0#
#991
b11011100 "
b11011100 *
1#
#992
0#
#993
b11011101 "
b11011101 *
1#
#994
0#
#995
b11011110 "
b11011110 *
1#
#996
0#
#997
b11011111 "
b11011111 *
1#
#998
0#
#999
b11100000 "
b11100000 *
1#
#1000
0#
#1001
b11100001 "
b11100001 *
1#
#1002
0#
#1003
b11100010 "
b11100010 *
1#
#1004
0#
#1005
b11100011 "
b11100011 *
1#
#1006
0#
#1007
b11100100 "
b11100100 *
1#
#1008
0#
#1009
b11100101 "
b11100101 *
1#
#1010
0#
#1011
b11100110 "
b11100110 *
1#
#1012
0#
#1013
b11100111 "
b11100111 *
1#
#1014
0#
#1015
b11101000 "
b11101000 *
1#
#1016
0#
#1017
b11101001 "
b11101001 *
1#
#1018
0#
#1019
b11101010 "
b11101010 *
1#
#1020
0#
#1021
b11101011 "
b11101011 *
1#
#1022
0#
#1023
b11101100 "
b11101100 *
1#
#1024
0#
#1025
b11101101 "
b11101101 *
1#
#1026
0#
#1027
b11101110 "
b11101110 *
1#
#1028
0#
#1029
b11101111 "
b11101111 *
1#
#1030
0#
1%
#1031
b11111111 "
b11111111 *
1#
#1032
0#
#1033
1#
#1034
0#
#1035
b11111110 "
b11111110 *
1#
0'
0%
#1036
0#
#1037
b11111101 "
b11111101 *
1#
#1038
0#
#1039
b11111100 "
b11111100 *
1#
#1040
0#
#1041
b11111011 "
b11111011 *
1#
#1042
0#
#1043
b11111010 "
b11111010 *
1#
#1044
0#
#1045
b11111001 "
b11111001 *
1#
#1046
0#
#1047
b11111000 "
b11111000 *
1#
#1048
0#
#1049
b11110111 "
b11110111 *
1#
#1050
0#
#1051
b11110110 "
b11110110 *
1#
#1052
0#
#1053
b11110101 "
b11110101 *
1#
#1054
0#
#1055
b11110100 "
b11110100 *
1#
#1056
0#
#1057
b11110011 "
b11110011 *
1#
#1058
0#
#1059
b11110010 "
b11110010 *
1#
#1060
0#
#1061
b11110001 "
b11110001 *
1#
#1062
0#
#1063
b11110000 "
b11110000 *
1#
#1064
0#
#1065
b11101111 "
b11101111 *
1#
#1066
0#
#1067
b11101110 "
b11101110 *
1#
#1068
0#
#1069
b11101101 "
b11101101 *
1#
#1070
0#
#1071
b11101100 "
b11101100 *
1#
#1072
0#
#1073
b11101011 "
b11101011 *
1#
#1074
0#
#1075
b11101010 "
b11101010 *
1#
#1076
0#
#1077
b11101001 "
b11101001 *
1#
#1078
0#
#1079
b11101000 "
b11101000 *
1#
#1080
0#
#1081
b11100111 "
b11100111 *
1#
#1082
0#
#1083
b11100110 "
b11100110 *
1#
#1084
0#
