BIST/controller/controller.v
module control (clk, rst, start, c_out, status, done, wr_en, read_en, rst_adr, pr_res_adr, enable, up_down, data_bit );

input clk, rst, start, c_out;
output reg status, done, wr_en, read_en, rst_adr, pr_res_adr, enable, up_down, data_bit;

localparam standby   = 3'b001;
localparam wr_up     = 3'b010;
localparam read_down = 3'b011;
localparam wr_down   = 3'b100;
localparam read_up   = 3'b101;

reg [2:0] state, next_state;

always@(posedge clk)begin
		if(rst) begin
				state<=standby;
				wr_en<=1'b0;
				read_en<=1'b0;
				rst_adr<=1'b0;
			   	pr_res_adr<=1'b0;
				enable<=1'b0;
				up_down<=1'b0;
				data_bit<=1'b0;
		end
		else begin
		state<=next_state;
		end
end

always@(*) begin

		case(state)
				standby: begin                //001
						if(start)begin
							enable=1'b1;
							rst_adr=1'b1;
							pr_res_adr=1'b0;
							read_en=1'b0;
							wr_en= 1'b1;
							up_down = 1'b1;
							data_bit=1'b0;
							next_state=wr_up;
						end 
						else begin
							enable=1'b0;
							rst_adr=1'b0;
							pr_res_adr=1'b0;
							read_en=1'b0;
							wr_en= 1'b0;
							up_down = 1'b0;
							data_bit=1'b0;
						end
				end
				wr_up: begin                   //010
						if(c_out)begin
							enable=1'b1;
							rst_adr=1'b0;
							pr_res_adr=1'b1;
							read_en=1'b1;
							wr_en= 1'b0;
							up_down = 1'b0;
							data_bit=1'b0;
							next_state=read_down;
						end 
						else begin
							enable=1'b1;
							rst_adr=1'b0;
							pr_res_adr=1'b0;
							read_en=1'b0;
							wr_en= 1'b1;
							up_down = 1'b1;
							data_bit=1'b0;
						end


				end
				read_down: begin                 //011
						if(c_out)begin
							enable=1'b1;
							rst_adr=1'b0;
							pr_res_adr=1'b1;
							read_en=1'b0;
							wr_en= 1'b1;
							up_down = 1'b0;
							data_bit=1'b1;
							next_state=wr_down;
						end 
						else begin
							enable=1'b1;
							rst_adr=1'b0;
							pr_res_adr=1'b0;
							read_en=1'b1;
							wr_en= 1'b0;
							up_down = 1'b0;
							data_bit=1'b0;
						end

				end
				wr_down: begin                   //100
						if(c_out)begin
							enable=1'b1;
							rst_adr=1'b1;
							pr_res_adr=1'b0;
							read_en=1'b1;
							wr_en= 1'b0;
							up_down = 1'b1;
							data_bit=1'b1;
							next_state=read_up;
						end 
						else begin
							enable=1'b1;
							rst_adr=1'b0;
							pr_res_adr=1'b0;
							read_en=1'b0;
							wr_en= 1'b1;
							up_down = 1'b0;
							data_bit=1'b1;
						end

				end
				read_up: begin                   //101
						if(c_out)begin
							next_state=standby;
						end 
						else begin
							enable=1'b1;
							rst_adr=1'b0;
							pr_res_adr=1'b0;
							read_en=1'b1;
							wr_en= 1'b0;
							up_down = 1'b1;
							data_bit=1'b1;
						end

				end
				default:
						state = standby;
		endcase
end

endmodule

BIST/controller/tbcntrl.v
module tbctr ();

reg clk, rst, start, c_out;

wire status, done;



//control bist (clk, rst, start, status, done);
control ctrl (clk, rst, start, c_out, status, done, wr_en, read_en, rst_adr, pr_res_adr, enable, up_down, data_bit );

always #1 clk = ~clk;
initial begin
    clk=1'b0;
    $dumpfile("mem.vcd");
    $dumpvars();
    end

initial begin
	rst=1'b0;
	start=1'b0;
	c_out=1'b0;
	#20;
	rst=1'b1;
	start=1'b0;
	c_out=1'b0;
	#2;
	rst=1'b0;
	start=1'b0;
	c_out=1'b0;
	#200;
	rst=1'b0;
	start=1'b1;
	c_out=1'b0;
	#1;
	start=1'b0;
	#210;
	rst=1'b0;
	start=1'b0;
	c_out=1'b1;
	#1
	c_out=1'b0;
	#210;
	rst=1'b0;
	start=1'b0;
	c_out=1'b1;
	#1
	c_out=1'b0;
	#210;
	rst=1'b0;
	start=1'b0;
	c_out=1'b1;
	#1
	c_out=1'b0;
	#210;
	rst=1'b0;
	start=1'b0;
	c_out=1'b1;
	#1
	c_out=1'b0;
	#210;
	rst=1'b0;
	start=1'b0;
	c_out=1'b1;
	#1
	c_out=1'b0;
	#20;
	$finish;

end
endmodule

BIST/controller/mem.vcd
$date
	Tue Jun 27 00:29:56 2023
$end
$version
	Icarus Verilog
$end
$timescale
	1s
$end
$scope module tbctr $end
$var wire 1 ! wr_en $end
$var wire 1 " up_down $end
$var wire 1 # status $end
$var wire 1 $ rst_adr $end
$var wire 1 % read_en $end
$var wire 1 & pr_res_adr $end
$var wire 1 ' enable $end
$var wire 1 ( done $end
$var wire 1 ) data_bit $end
$var reg 1 * c_out $end
$var reg 1 + clk $end
$var reg 1 , rst $end
$var reg 1 - start $end
$scope module ctrl $end
$var wire 1 * c_out $end
$var wire 1 + clk $end
$var wire 1 , rst $end
$var wire 1 - start $end
$var reg 1 ) data_bit $end
$var reg 1 ( done $end
$var reg 1 ' enable $end
$var reg 3 . next_state [2:0] $end
$var reg 1 & pr_res_adr $end
$var reg 1 % read_en $end
$var reg 1 $ rst_adr $end
$var reg 3 / state [2:0] $end
$var reg 1 # status $end
$var reg 1 " up_down $end
$var reg 1 ! wr_en $end
$upscope $end
$upscope $end
$enddefinitions $end
#0
$dumpvars
b1 /
bx .
0-
0,
0+
0*
x)
x(
x'
x&
x%
x$
x#
x"
x!
$end
#1
b1 /
1+
#2
0+
#3
b1 /
1+
#4
0+
#5
b1 /
1+
#6
0+
#7
b1 /
1+
#8
0+
#9
b1 /
1+
#10
0+
#11
b1 /
1+
#12
0+
#13
b1 /
1+
#14
0+
#15
b1 /
1+
#16
0+
#17
b1 /
1+
#18
0+
#19
b1 /
1+
#20
0+
1,
#21
0)
0"
0'
0&
0$
0%
0!
1+
#22
0+
0,
#23
b1 /
1+
#24
0+
#25
b1 /
1+
#26
0+
#27
b1 /
1+
#28
0+
#29
b1 /
1+
#30
0+
#31
b1 /
1+
#32
0+
#33
b1 /
1+
#34
0+
#35
b1 /
1+
#36
0+
#37
b1 /
1+
#38
0+
#39
b1 /
1+
#40
0+
#41
b1 /
1+
#42
0+
#43
b1 /
1+
#44
0+
#45
b1 /
1+
#46
0+
#47
b1 /
1+
#48
0+
#49
b1 /
1+
#50
0+
#51
b1 /
1+
#52
0+
#53
b1 /
1+
#54
0+
#55
b1 /
1+
#56
0+
#57
b1 /
1+
#58
0+
#59
b1 /
1+
#60
0+
#61
b1 /
1+
#62
0+
#63
b1 /
1+
#64
0+
#65
b1 /
1+
#66
0+
#67
b1 /
1+
#68
0+
#69
b1 /
1+
#70
0+
#71
b1 /
1+
#72
0+
#73
b1 /
1+
#74
0+
#75
b1 /
1+
#76
0+
#77
b1 /
1+
#78
0+
#79
b1 /
1+
#80
0+
#81
b1 /
1+
#82
0+
#83
b1 /
1+
#84
0+
#85
b1 /
1+
#86
0+
#87
b1 /
1+
#88
0+
#89
b1 /
1+
#90
0+
#91
b1 /
1+
#92
0+
#93
b1 /
1+
#94
0+
#95
b1 /
1+
#96
0+
#97
b1 /
1+
#98
0+
#99
b1 /
1+
#100
0+
#101
b1 /
1+
#102
0+
#103
b1 /
1+
#104
0+
#105
b1 /
1+
#106
0+
#107
b1 /
1+
#108
0+
#109
b1 /
1+
#110
0+
#111
b1 /
1+
#112
0+
#113
b1 /
1+
#114
0+
#115
b1 /
1+
#116
0+
#117
b1 /
1+
#118
0+
#119
b1 /
1+
#120
0+
#121
b1 /
1+
#122
0+
#123
b1 /
1+
#124
0+
#125
b1 /
1+
#126
0+
#127
b1 /
1+
#128
0+
#129
b1 /
1+
#130
0+
#131
b1 /
1+
#132
0+
#133
b1 /
1+
#134
0+
#135
b1 /
1+
#136
0+
#137
b1 /
1+
#138
0+
#139
b1 /
1+
#140
0+
#141
b1 /
1+
#142
0+
#143
b1 /
1+
#144
0+
#145
b1 /
1+
#146
0+
#147
b1 /
1+
#148
0+
#149
b1 /
1+
#150
0+
#151
b1 /
1+
#152
0+
#153
b1 /
1+
#154
0+
#155
b1 /
1+
#156
0+
#157
b1 /
1+
#158
0+
#159
b1 /
1+
#160
0+
#161
b1 /
1+
#162
0+
#163
b1 /
1+
#164
0+
#165
b1 /
1+
#166
0+
#167
b1 /
1+
#168
0+
#169
b1 /
1+
#170
0+
#171
b1 /
1+
#172
0+
#173
b1 /
1+
#174
0+
#175
b1 /
1+
#176
0+
#177
b1 /
1+
#178
0+
#179
b1 /
1+
#180
0+
#181
b1 /
1+
#182
0+
#183
b1 /
1+
#184
0+
#185
b1 /
1+
#186
0+
#187
b1 /
1+
#188
0+
#189
b1 /
1+
#190
0+
#191
b1 /
1+
#192
0+
#193
b1 /
1+
#194
0+
#195
b1 /
1+
#196
0+
#197
b1 /
1+
#198
0+
#199
b1 /
1+
#200
0+
#201
b1 /
1+
#202
0+
#203
b1 /
1+
#204
0+
#205
b1 /
1+
#206
0+
#207
b1 /
1+
#208
0+
#209
b1 /
1+
#210
0+
#211
b1 /
1+
#212
0+
#213
b1 /
1+
#214
0+
#215
b1 /
1+
#216
0+
#217
b1 /
1+
#218
0+
#219
b1 /
1+
#220
0+
#221
b1 /
1+
#222
b10 .
1"
1!
1$
1'
0+
1-
#223
b10 /
1"
1!
0$
1'
1+
0-
